{
	"timeline":{
		"headline":"丸子家...",
		"type":"default",
		"text":"巴巴是怎么搞掂麻麻绝代风华的?...益rz",
		"startDate":"1990,05,05",
		"date":[
			{
				"id":"130925",
				"startDate":"2013,09,25",
				"headline":" 新产品推广",
				"text":"南京境中使用。并具有坚实、耐用、抗折、不起皮、抗暴晒、抗风性强等特点。",
				"media":"http://zoomq.qiniudn.com/ZQCollection/img/yw_flat-earth.png",
				"asset":{
					"media":"http://zoomq.qiniudn.com/ZQCollection/img/yw_flat-earth.png"
				}
			},
			{
				"id":"131029",
				"startDate":"2013,10,29",
				"headline":"三川房”收获丰盛，品牌效应大放光彩！",
				"text":"    201戈雷",
				"media":"http://sanchuan.pavilion-china.com/uploaded/news/20131027_0920322.jpg",
				"asset":{
					"media":"http://sanchuan.pavilion-china.com/uploaded/news/20131027_0920322.jpg"
				}
			},
		]
	}
}